MathIsCool/__init__.py
MathIsCool/main.py
MathIsCool-0.4.0.dist-info/METADATA
MathIsCool-0.4.0.dist-info/WHEEL
MathIsCool-0.4.0.dist-info/top_level.txt
MathIsCool-0.4.0.dist-info/RECORD
