Metadata-Version: 2.1
Name: MathIsCool
Version: 0.4.0
Requires-Dist: bestErrors >=0.1
